quickpomdps/__init__.py
quickpomdps/setup.jl
quickpomdps-0.1.2.dist-info/LICENSE
quickpomdps-0.1.2.dist-info/METADATA
quickpomdps-0.1.2.dist-info/WHEEL
quickpomdps-0.1.2.dist-info/RECORD
