Metadata-Version: 2.1
Name: quickpomdps
Version: 0.1.2
Summary: Describing and Solving POMDPs in Python
Home-page: https://github.com/JuliaPOMDP/quickpomdps/
License: MIT
Author: rejuvyesh
Author-email: mail@rejuvyesh.com
Requires-Python: >=3.7,<4.0
Classifier: License :: OSI Approved :: MIT License
Classifier: Programming Language :: Python :: 3
Classifier: Programming Language :: Python :: 3.7
Classifier: Programming Language :: Python :: 3.8
Classifier: Programming Language :: Python :: 3.9
Classifier: Programming Language :: Python :: 3.10
Classifier: Programming Language :: Python :: 3.11
Requires-Dist: julia (>=0.5,<0.7)
Project-URL: Repository, https://github.com/JuliaPOMDP/quickpomdps/
